generalized_naive_bayes/__init__.py
generalized_naive_bayes/core/__init__.py
generalized_naive_bayes/core/classifier.py
generalized_naive_bayes/utils/__init__.py
generalized_naive_bayes/utils/types.py
generalized_naive_bayes/utils/utils.py
generalized_naive_bayes-0.0.3.dist-info/WHEEL
generalized_naive_bayes-0.0.3.dist-info/entry_points.txt
generalized_naive_bayes-0.0.3.dist-info/METADATA
generalized_naive_bayes-0.0.3.dist-info/RECORD
