Metadata-Version: 2.3
Name: generalized-naive-bayes
Version: 0.0.3
Summary: Add your description here
Requires-Dist: numpy>=2.3.2
Requires-Python: >=3.11
